temboard-9.0.1.data/data/lib/systemd/system/temboard.service
temboard-9.0.1.data/data/share/temboard/auto_configure.sh
temboard-9.0.1.data/data/share/temboard/create_repository.sh
temboard-9.0.1.data/data/share/temboard/postinst.sh
temboard-9.0.1.data/data/share/temboard/preun.sh
temboard-9.0.1.data/data/share/temboard/purge.sh
temboard-9.0.1.data/data/share/temboard/quickstart/temboard.conf
temboard-9.0.1.data/data/share/temboard/quickstart/temboard_CHANGEME.key
temboard-9.0.1.data/data/share/temboard/quickstart/temboard_CHANGEME.pem
temboard-9.0.1.data/data/share/temboard/quickstart/temboard_ca_certs_CHANGEME.pem
temboard-9.0.1.data/data/share/temboard/sql/dev-fixture.sql
temboard-9.0.1.data/data/share/temboard/sql/reassign.sql
temboard-9.0.1.data/data/share/temboard/sql/upgrade-monitoring-purge-instances.sql
temboardui/__init__.py
temboardui/__main__.py
temboardui/agentclient.py
temboardui/application.py
temboardui/autossl.py
temboardui/core.py
temboardui/errors.py
temboardui/version.py
temboardui/cli/__init__.py
temboardui/cli/apikey.py
temboardui/cli/app.py
temboardui/cli/generate_key.py
temboardui/cli/migratedb.py
temboardui/cli/prometheus.py
temboardui/cli/query_agent.py
temboardui/cli/register_instance.py
temboardui/cli/routes.py
temboardui/cli/serve.py
temboardui/cli/tasks.py
temboardui/cli/web.py
temboardui/handlers/__init__.py
temboardui/handlers/notification.py
temboardui/handlers/settings/__init__.py
temboardui/handlers/settings/metadata.py
temboardui/model/__init__.py
temboardui/model/migrator.py
temboardui/model/orm.py
temboardui/model/queries/apikeys-delete.sql
temboardui/model/queries/apikeys-insert.sql
temboardui/model/queries/apikeys-purge.sql
temboardui/model/queries/apikeys-select-active.sql
temboardui/model/queries/apikeys-select-secret.sql
temboardui/model/queries/environment-memberships.sql
temboardui/model/queries/environments-all.sql
temboardui/model/queries/environments-get.sql
temboardui/model/queries/group-delete-membership.sql
temboard-9.0.1.dist-info/LICENSE
temboard-9.0.1.dist-info/METADATA
temboard-9.0.1.dist-info/WHEEL
temboard-9.0.1.dist-info/entry_points.txt
temboard-9.0.1.dist-info/top_level.txt
temboard-9.0.1.dist-info/RECORD
