Metadata-Version: 2.1
Name: temboard
Version: 9.0.1
Summary: temBoard User Interface.
Home-page: https://labs.dalibo.com/temboard
Author: Dalibo
Author-email: contact@dalibo.com
License: PostgreSQL
Platform: UNKNOWN
Classifier: Intended Audience :: System Administrators
Classifier: License :: OSI Approved
Classifier: Operating System :: POSIX :: Linux
Classifier: Programming Language :: Python :: 3.6
Classifier: Topic :: Database :: Database Engines/Servers
Classifier: Topic :: System :: Monitoring
Requires-Dist: cryptography
Requires-Dist: flask
Requires-Dist: future
Requires-Dist: python-dateutil (>=1.5)
Requires-Dist: setuptools
Requires-Dist: sqlalchemy (<2,>=1.3.2)
Requires-Dist: tornado (<6.5,>=6.0.2)
